{
  "parent": "minecraft:recipes/root",
  "criteria": {
    "has_blue_aercloud": {
      "conditions": {
        "items": [
          {
            "items": [
              "aether:blue_aercloud"
            ]
          }
        ]
      },
      "trigger": "minecraft:inventory_changed"
    },
    "has_the_recipe": {
      "conditions": {
        "recipe": "genesis:blue_parachute"
      },
      "trigger": "minecraft:recipe_unlocked"
    }
  },
  "requirements": [
    [
      "has_blue_aercloud",
      "has_the_recipe"
    ]
  ],
  "rewards": {
    "recipes": [
      "genesis:blue_parachute"
    ]
  }
}